una/__init__.py
una/__main__.py
una/check.py
una/cli.py
una/config.py
una/consts.py
una/distributions.py
una/files.py
una/models.py
una/package_deps.py
una/parse.py
una/py.typed
una/stdlib.py
una/sync.py
una-0.6.5.dist-info/METADATA
una-0.6.5.dist-info/WHEEL
una-0.6.5.dist-info/entry_points.txt
una-0.6.5.dist-info/RECORD
