Metadata-Version: 2.4
Name: una
Version: 0.6.5
Summary: Python monorepo tooling
Project-URL: homepage, https://github.com/carderne/una
Project-URL: repository, https://github.com/carderne/una
Author-email: Chris Arderne <chris@rdrn.me>
License: MIT License
Keywords: build,monorepo,python,uv
Classifier: Environment :: Console
Classifier: Intended Audience :: Developers
Classifier: License :: OSI Approved :: MIT License
Classifier: Operating System :: Unix
Classifier: Programming Language :: Python
Classifier: Programming Language :: Python :: 3.10
Classifier: Programming Language :: Python :: 3.11
Classifier: Programming Language :: Python :: 3.12
Requires-Python: >=3.11
Requires-Dist: dataclasses-json~=0.6
Requires-Dist: rich~=13.1
Requires-Dist: tomlkit~=0.10
Requires-Dist: typer~=0.15.4
